{"cameraMode":{"drawMode":0,"name":"Shaded","section":"Shading Mode"},"sceneLighting":false,"audioPlay":false,"sceneViewState":{"showFog":true,"showMaterialUpdate":false,"showSkybox":false,"showFlares":true,"showImageEffects":true,"showParticleSystems":true,"showVisualEffectGraphs":true,"m_FxEnabled":true},"in2DMode":false,"pivot":{"x":0.0,"y":0.3999999463558197,"z":0.0},"rotation":{"x":0.0491262786090374,"y":0.042532581835985187,"z":0.002092696027830243,"w":-0.9978882074356079},"size":1.2951061725616456,"orthographic":false}